gen_vm_image/__init__.py
gen_vm_image/_version.py
gen_vm_image/architecture.py
gen_vm_image/image.py
gen_vm_image/cli/__init__.py
gen_vm_image/cli/cli.py
gen_vm_image/cli/common.py
gen_vm_image/cli/corc.py
gen_vm_image/cli/helpers.py
gen_vm_image/cli/input_groups/__init__.py
gen_vm_image/cli/input_groups/multiple.py
gen_vm_image/cli/input_groups/single.py
gen_vm_image/cli/operations/__init__.py
gen_vm_image/cli/operations/multiple/__init__.py
gen_vm_image/cli/operations/multiple/build.py
gen_vm_image/cli/operations/single/__init__.py
gen_vm_image/cli/operations/single/build.py
gen_vm_image/cli/parsers/__init__.py
gen_vm_image/cli/parsers/actions.py
gen_vm_image/cli/parsers/multiple.py
gen_vm_image/cli/parsers/single.py
gen_vm_image/common/__init__.py
gen_vm_image/common/codes.py
gen_vm_image/common/defaults.py
gen_vm_image/utils/__init__.py
gen_vm_image/utils/io.py
gen_vm_image/utils/job.py
gen_vm_image/utils/net.py
gen_vm_image/utils/user.py
tests/__init__.py
tests/context.py
tests/test_architecture_file.py
tests/test_cli_base.py
tests/test_cli_multiple_image.py
tests/test_cli_single_image.py
tests/test_image_core.py
gen_vm_image-0.0.7.dist-info/LICENSE
gen_vm_image-0.0.7.dist-info/METADATA
gen_vm_image-0.0.7.dist-info/WHEEL
gen_vm_image-0.0.7.dist-info/entry_points.txt
gen_vm_image-0.0.7.dist-info/top_level.txt
gen_vm_image-0.0.7.dist-info/RECORD
